Metadata-Version: 2.1
Name: pyabaqus
Version: 2021.1
Summary: Type hints for Abaqus/Python scripting
Home-page: https://github.com/haiiliin/pyabaqus
Author: WANG Hailin
Author-email: hailin.wang@connect.polyu.hk
License: UNKNOWN
Platform: UNKNOWN
Classifier: Programming Language :: Python :: 3.9
Classifier: Programming Language :: Python :: 3.10
Classifier: License :: OSI Approved :: MIT License
Classifier: Operating System :: OS Independent
Requires-Python: >=3.9
License-File: LICENSE
Requires-Dist: ipyparams
